README.md
setup.cfg
setup.py
xSH01.py
xinabox_SH01.egg-info/PKG-INFO
xinabox_SH01.egg-info/SOURCES.txt
xinabox_SH01.egg-info/dependency_links.txt
xinabox_SH01.egg-info/requires.txt
xinabox_SH01.egg-info/top_level.txt